LICENSE
README.md
setup.cfg
setup.py
cosasi/__init__.py
cosasi.egg-info/PKG-INFO
cosasi.egg-info/SOURCES.txt
cosasi.egg-info/dependency_links.txt
cosasi.egg-info/top_level.txt
cosasi/benchmark/__init__.py
cosasi/benchmark/benchmark.py
cosasi/benchmark/tests/__init__.py
cosasi/benchmark/tests/test_benchmark.py
cosasi/contagion/__init__.py
cosasi/contagion/static_network_contagion.py
cosasi/contagion/tests/__init__.py
cosasi/contagion/tests/test_static_network_contagion.py
cosasi/source_inference/__init__.py
cosasi/source_inference/algorithm_details.json
cosasi/source_inference/source_results.py
cosasi/source_inference/multiple_source/__init__.py
cosasi/source_inference/multiple_source/jordan.py
cosasi/source_inference/multiple_source/lisn.py
cosasi/source_inference/multiple_source/netsleuth.py
cosasi/source_inference/multiple_source/tests/__init__.py
cosasi/source_inference/multiple_source/tests/test_jordan.py
cosasi/source_inference/multiple_source/tests/test_lisn.py
cosasi/source_inference/multiple_source/tests/test_netsleuth.py
cosasi/source_inference/single_source/__init__.py
cosasi/source_inference/single_source/earliest_infection_first.py
cosasi/source_inference/single_source/jordan.py
cosasi/source_inference/single_source/lisn.py
cosasi/source_inference/single_source/netsleuth.py
cosasi/source_inference/single_source/rumor_centrality.py
cosasi/source_inference/single_source/short_fat_tree.py
cosasi/source_inference/single_source/tests/__init__.py
cosasi/source_inference/single_source/tests/test_earliest_infection_first.py
cosasi/source_inference/single_source/tests/test_jordan.py
cosasi/source_inference/single_source/tests/test_lisn.py
cosasi/source_inference/single_source/tests/test_netsleuth.py
cosasi/source_inference/single_source/tests/test_rumor_centrality.py
cosasi/source_inference/single_source/tests/test_short_fat_tree.py
cosasi/source_inference/tests/__init__.py
cosasi/source_inference/tests/test_source_results.py
cosasi/utils/__init__.py
cosasi/utils/estimators.py
cosasi/utils/helpers.py
cosasi/utils/tests/__init__.py
cosasi/utils/tests/test_estimators.py
