Metadata-Version: 2.1
Name: cosasi
Version: 0.0.3
Summary: COntagion Simulation And Source Identification
Home-page: https://github.com/lmiconsulting/cosasi
Author: Lucas H. McCabe
Author-email: lmccabe@lmi.org
License: UNKNOWN
Platform: UNKNOWN
Classifier: Programming Language :: Python :: 3
Classifier: License :: OSI Approved :: MIT License
Classifier: Operating System :: OS Independent
Requires-Python: >=3.8
